{
    "appKeys": {
        "KEY_CONDITIONS": 1,
        "KEY_PLACE": 2,
        "KEY_TEMPERATURE": 0
    },
    "capabilities": [
        "location"
    ],
    "companyName": "GCE",
    "longName": "GCE2_1",
    "projectType": "native",
    "resources": {
        "media": [
            {
                "file": "fonts/gcedruck.TTF",
                "name": "FONT_GCE_DRUCKSCHRIFT_55",
                "type": "font"
            },
            {
                "file": "fonts/gcedruck.TTF",
                "name": "FONT_GCE_DRUCKSCHRIFT_16",
                "type": "font"
            },
            {
                "file": "images/Georg_sw.png",
                "name": "IMAGE_GCE",
                "type": "png"
            }
        ]
    },
    "sdkVersion": "3",
    "shortName": "GCE2_1",
    "targetPlatforms": [
        "basalt"
    ],
    "uuid": "58dcb6e8-c289-4a54-9c24-d3af3a8a0826",
    "versionLabel": "1.0",
    "watchapp": {
        "watchface": true
    }
}
